project_context/__init__.py
project_context/main.py
project_context/tree.py
project_context/utils.py
project_context-0.2.0.dist-info/METADATA
project_context-0.2.0.dist-info/WHEEL
project_context-0.2.0.dist-info/entry_points.txt
project_context-0.2.0.dist-info/licenses/LICENSE
project_context-0.2.0.dist-info/RECORD
