Metadata-Version: 2.4
Name: project-context
Version: 0.2.0
Summary: Generate LLM-friendly markdown from your project files.
Author-email: Jeff Moore <jeffreymm@protonmail.com>
License-File: LICENSE
Requires-Python: >=3.11
Requires-Dist: click>=8.2.1
Requires-Dist: jinja2>=3.1.6
